Errome/Errome.py
Errome/__init__.py
Errome/templates/__init__.py
Errome/templates/erro.html
Errome/templates/ok.html
Errome/templates/start.html
errome-0.3.4.dist-info/METADATA
errome-0.3.4.dist-info/WHEEL
errome-0.3.4.dist-info/top_level.txt
errome-0.3.4.dist-info/RECORD
