Metadata-Version: 2.2
Name: Errome
Version: 0.3.4
Summary: A program error or completion email notification tool.
Home-page: https://github.com/Becomingw/Errome.git
Author: BecomingW
Author-email: Becomingw@qq.com
Requires-Dist: importlib-resources; python_version < "3.9"
Dynamic: author
Dynamic: author-email
Dynamic: description
Dynamic: description-content-type
Dynamic: home-page
Dynamic: requires-dist
Dynamic: summary
